pts_hmp4040_psu/__init__.py
pts_hmp4040_psu/hmp4040_psu.py
pts_hmp4040_psu-0.0.6.dist-info/LICENSE.txt
pts_hmp4040_psu-0.0.6.dist-info/METADATA
pts_hmp4040_psu-0.0.6.dist-info/WHEEL
pts_hmp4040_psu-0.0.6.dist-info/top_level.txt
pts_hmp4040_psu-0.0.6.dist-info/RECORD
